twd/__init__.py
twd/twd.py
twd-0.0.3.dist-info/LICENSE
twd-0.0.3.dist-info/METADATA
twd-0.0.3.dist-info/WHEEL
twd-0.0.3.dist-info/top_level.txt
twd-0.0.3.dist-info/RECORD
