Metadata-Version: 2.1
Name: twd
Version: 0.0.3
Summary: Three Way Decision/Rough Set library
Home-page: https://github.com/profssribeiro/twd
Author: Sergio S. Ribeiro
Author-email: profssribeiro@gmail.com
License: MIT License
Keywords: Pacote
Platform: UNKNOWN
